blackclue.py
blackvue_acc.py
blackvue_acc-2018.7.26.dist-info/METADATA
blackvue_acc-2018.7.26.dist-info/RECORD
blackvue_acc-2018.7.26.dist-info/WHEEL
blackvue_acc-2018.7.26.dist-info/entry_points.txt
blackvue_acc-2018.7.26.dist-info/top_level.txt
