Metadata-Version: 2.1
Name: blackvue-acc
Version: 2018.7.26
Summary: Parse accelerometer records created by BlackVue Dashcams.
Home-page: https://github.com/bartbroere/blackvue-acc/
Author: Bart Broere
Author-email: maiil@bartbroere.eu
License: MIT License
Keywords: blackvue accelerometer gforce dashcam 3gf parse parser
Platform: UNKNOWN
Classifier: License :: OSI Approved :: MIT License
Classifier: Programming Language :: Python :: 3 :: Only
Classifier: Programming Language :: Python :: 3.4
Classifier: Programming Language :: Python :: 3.5
Classifier: Programming Language :: Python :: 3.6
Classifier: Programming Language :: Python :: 3.7
Classifier: Topic :: Utilities
Requires-Dist: click
Requires-Dist: docopt
Requires-Dist: pandas
Requires-Dist: pymp4
